py3_Wordsmith/__init__.py
py3_Wordsmith/wordsmith.py
py3_wordsmith-1.1.1.dist-info/DESCRIPTION.rst
py3_wordsmith-1.1.1.dist-info/METADATA
py3_wordsmith-1.1.1.dist-info/RECORD
py3_wordsmith-1.1.1.dist-info/WHEEL
py3_wordsmith-1.1.1.dist-info/metadata.json
py3_wordsmith-1.1.1.dist-info/pbr.json
py3_wordsmith-1.1.1.dist-info/top_level.txt
