Metadata-Version: 2.0
Name: py3-wordsmith
Version: 1.1.1
Summary: API for Wordsmith
Home-page: https://github.com/xACruceSalus/py3_wordsmith
Author: ['Zack Cooper', 'John Hegele']
Author-email: zackjcooper@gmail.com
License: MIT
Keywords: wordsmith api
Platform: UNKNOWN
Classifier: Development Status :: 4 - Beta
Classifier: Intended Audience :: Developers
Classifier: Programming Language :: Python :: 3.3
Classifier: Programming Language :: Python :: 3.4
Classifier: License :: OSI Approved :: MIT License
